missive/__init__.py
missive/messages.py
missive/missive.py
missive/py.typed
missive/shutdown_handler.py
missive/state.py
missive/adapters/__init__.py
missive/adapters/rabbitmq.py
missive/adapters/redis.py
missive/adapters/stdin.py
missive/adapters/wsgi.py
missive/dlq/__init__.py
missive/dlq/file.py
missive/dlq/sqlite.py
missive-0.8.1.dist-info/METADATA
missive-0.8.1.dist-info/WHEEL
missive-0.8.1.dist-info/top_level.txt
missive-0.8.1.dist-info/zip-safe
missive-0.8.1.dist-info/RECORD
