Metadata-Version: 2.1
Name: missive
Version: 0.8.1
Summary: UNKNOWN
Home-page: UNKNOWN
License: UNKNOWN
Platform: UNKNOWN
Requires-Dist: flask
Requires-Dist: redis
Requires-Dist: kombu
Provides-Extra: dev
Requires-Dist: sphinx (~=2.4.3) ; extra == 'dev'
Requires-Dist: wheel (~=0.33.6) ; extra == 'dev'
Requires-Dist: black (~=19.10b0) ; extra == 'dev'
Requires-Dist: mypy (~=0.750) ; extra == 'dev'
Requires-Dist: bpython (~=0.18) ; extra == 'dev'
Requires-Dist: flake8 (==3.7.9) ; extra == 'dev'
Provides-Extra: tests
Requires-Dist: pytest (~=5.3.1) ; extra == 'tests'
Requires-Dist: pytest-cov (~=2.8.1) ; extra == 'tests'
Requires-Dist: freezegun (==0.3.15) ; extra == 'tests'
